code_size_analyzer_client/__init__.py
code_size_analyzer_client/api_client.py
code_size_analyzer_client/api_response.py
code_size_analyzer_client/client_wrapper.py
code_size_analyzer_client/code_size_analyzer_cli.py
code_size_analyzer_client/code_size_results_cli.py
code_size_analyzer_client/configuration.py
code_size_analyzer_client/exceptions.py
code_size_analyzer_client/py.typed
code_size_analyzer_client/rest.py
code_size_analyzer_client/api/__init__.py
code_size_analyzer_client/api/analyzer_api.py
code_size_analyzer_client/api/asyncapi_api.py
code_size_analyzer_client/api/default_api.py
code_size_analyzer_client/api/parser_api.py
code_size_analyzer_client/api/results_api.py
code_size_analyzer_client/models/__init__.py
code_size_analyzer_client/models/application_analysis_result_with_detail.py
code_size_analyzer_client/models/application_combination.py
code_size_analyzer_client/models/classification_rule.py
code_size_analyzer_client/models/data_record.py
code_size_analyzer_client/models/file_data.py
code_size_analyzer_client/models/http_validation_error.py
code_size_analyzer_client/models/map_file_memory_config.py
code_size_analyzer_client/models/map_file_parse_request.py
code_size_analyzer_client/models/map_file_parse_response.py
code_size_analyzer_client/models/map_file_request.py
code_size_analyzer_client/models/map_file_response.py
code_size_analyzer_client/models/map_file_section.py
code_size_analyzer_client/models/map_file_summary.py
code_size_analyzer_client/models/module.py
code_size_analyzer_client/models/module_group.py
code_size_analyzer_client/models/response_get_app_analysis_details.py
code_size_analyzer_client/models/section_summary.py
code_size_analyzer_client/models/summary_record.py
code_size_analyzer_client/models/symbol.py
code_size_analyzer_client/models/target_info.py
code_size_analyzer_client/models/validation_error.py
code_size_analyzer_client/models/validation_error_loc_inner.py
code_size_analyzer_client_python-1.2.0.dist-info/METADATA
code_size_analyzer_client_python-1.2.0.dist-info/WHEEL
code_size_analyzer_client_python-1.2.0.dist-info/entry_points.txt
code_size_analyzer_client_python-1.2.0.dist-info/top_level.txt
code_size_analyzer_client_python-1.2.0.dist-info/RECORD
