Metadata-Version: 2.4
Name: code_size_analyzer_client-python
Version: 1.2.0
Summary: FastAPI
Author-email: OpenAPI Generator Community <team@openapitools.org>
Project-URL: Repository, https://github.com/GIT_USER_ID/GIT_REPO_ID
Keywords: OpenAPI,OpenAPI-Generator,FastAPI
Requires-Python: >=3.10
Requires-Dist: urllib3<3.0.0,>=2.1.0
Requires-Dist: python-dateutil>=2.8.2
Requires-Dist: pydantic>=2
Requires-Dist: typing-extensions>=4.7.1
Requires-Dist: lazy-imports<2,>=1
Requires-Dist: click
Requires-Dist: opentelemetry-distro[otlp]
Requires-Dist: opentelemetry-instrumentation-urllib3
Requires-Dist: otel_extensions==1.*
Requires-Dist: retry
Requires-Dist: pyyaml
